.long-description.html
MANIFEST.in
README.txt
setup.py
bp/__init__.py
bp.logging.egg-info/PKG-INFO
bp.logging.egg-info/SOURCES.txt
bp.logging.egg-info/dependency_links.txt
bp.logging.egg-info/entry_points.txt
bp.logging.egg-info/namespace_packages.txt
bp.logging.egg-info/not-zip-safe
bp.logging.egg-info/requires.txt
bp.logging.egg-info/top_level.txt
bp/logging/__init__.py
docs/HISTORY.txt
docs/LICENSE.txt