Metadata-Version: 1.0
Name: bp.logging
Version: 0.2.1
Summary: Reduce logging related repetition in your code
Home-page: https://github.com/disko/bp.logging
Author: Andreas Kaiser
Author-email: disko@binary-punks.com
License: BSD
Keywords: logging
Platform: UNKNOWN
Classifier: Development Status :: 3 - Alpha
Classifier: Environment :: Console
Classifier: Intended Audience :: Developers
Classifier: Intended Audience :: System Administrators
Classifier: License :: OSI Approved :: BSD License
Classifier: Programming Language :: Python
